odoo8_addon_passport-8.0.0.1.0.99.dev17-py3.8-nspkg.pth
odoo_addons/passport/__init__.py
odoo_addons/passport/__openerp__.py
odoo_addons/passport/res_partner.py
odoo_addons/passport/res_partner_view.xml
odoo_addons/passport/res_passport.py
odoo_addons/passport/res_passport_view.xml
odoo_addons/passport/i18n/de.po
odoo_addons/passport/i18n/es.po
odoo_addons/passport/i18n/eu.po
odoo_addons/passport/i18n/fi.po
odoo_addons/passport/i18n/fr.po
odoo_addons/passport/i18n/it.po
odoo_addons/passport/i18n/nl.po
odoo_addons/passport/i18n/passport.pot
odoo_addons/passport/i18n/pt_BR.po
odoo_addons/passport/i18n/sl.po
odoo_addons/passport/security/ir.model.access.csv
odoo_addons/passport/static/description/icon.png
odoo_addons/passport/tests/__init__.py
odoo_addons/passport/tests/test_passport.py
odoo8_addon_passport-8.0.0.1.0.99.dev17.dist-info/METADATA
odoo8_addon_passport-8.0.0.1.0.99.dev17.dist-info/WHEEL
odoo8_addon_passport-8.0.0.1.0.99.dev17.dist-info/namespace_packages.txt
odoo8_addon_passport-8.0.0.1.0.99.dev17.dist-info/top_level.txt
odoo8_addon_passport-8.0.0.1.0.99.dev17.dist-info/RECORD
